DDos/__init__.py
DDos/__main__.py
DDos/proxies.txt
DDos-1.0.3.dist-info/LICENSE
DDos-1.0.3.dist-info/METADATA
DDos-1.0.3.dist-info/WHEEL
DDos-1.0.3.dist-info/entry_points.txt
DDos-1.0.3.dist-info/top_level.txt
DDos-1.0.3.dist-info/RECORD
