Metadata-Version: 2.1
Name: DDos
Version: 1.0.3
Summary: DDos any site
Home-page: https://github.com/donno2048/DDos
Author: Elisha Hollander
License: MIT
Platform: UNKNOWN
Classifier: Programming Language :: Python :: 3
License-File: LICENSE
Requires-Dist: fake-useragent
